milksnake/__init__.py
milksnake/_compat.py
milksnake/ffi.py
milksnake/setuptools_ext.py
pyromilksnakex-0.1.8.dist-info/LICENSE
pyromilksnakex-0.1.8.dist-info/METADATA
pyromilksnakex-0.1.8.dist-info/WHEEL
pyromilksnakex-0.1.8.dist-info/entry_points.txt
pyromilksnakex-0.1.8.dist-info/top_level.txt
pyromilksnakex-0.1.8.dist-info/RECORD
