Metadata-Version: 2.1
Name: pyromilksnakex
Version: 0.1.8
Summary: A python library that extends setuptools for binary extensions.
Home-page: UNKNOWN
Author: Armin Ronacher, Abid Omar
Author-email: armin.ronacher@active-4.com, contact@omarabid.com
License: Apache License 2.0
Platform: any
Classifier: License :: OSI Approved :: Apache Software License
Classifier: Programming Language :: Python
License-File: LICENSE
Requires-Dist: cffi (>=1.6.0)
